llama_index/embeddings/clip/__init__.py
llama_index/embeddings/clip/base.py
llama_index_embeddings_clip-0.5.1.dist-info/METADATA
llama_index_embeddings_clip-0.5.1.dist-info/WHEEL
llama_index_embeddings_clip-0.5.1.dist-info/licenses/LICENSE
llama_index_embeddings_clip-0.5.1.dist-info/RECORD
